nlidatamanagement/__init__.py
nlidatamanagement/main.py
nlidatamanagement/tags.py
nlidatamanagement/imgs/__init__.py
nlidatamanagement/imgs/add.png
nlidatamanagement/imgs/add_folder.png
nlidatamanagement/imgs/back.png
nlidatamanagement/imgs/connect.png
nlidatamanagement/imgs/delete.png
nlidatamanagement/imgs/download.png
nlidatamanagement/imgs/folder.png
nlidatamanagement/imgs/go.png
nlidatamanagement/imgs/refresh.png
nlidatamanagement/imgs/remove.png
nlidatamanagement/imgs/setting.png
nlidatamanagement/imgs/upload.png
nlidatamanagement/utils/__init__.py
nlidatamanagement/utils/girder_connector.py
nlidatamanagement/utils/girder_instance.py
nlidatamanagement/utils/parser.py
nlidatamanagement/utils/zotero_connector.py
nlidatamanagement/utils/zotero_instance.py
nlidatamanagement/views/__init__.py
nlidatamanagement/views/common/__init__.py
nlidatamanagement/views/common/item_info.py
nlidatamanagement/views/common/setting.py
nlidatamanagement/views/girder/__init__.py
nlidatamanagement/views/girder/girder_choose_file.py
nlidatamanagement/views/girder/girder_download.py
nlidatamanagement/views/girder/girder_entry.py
nlidatamanagement/views/girder/girder_file_system.py
nlidatamanagement/views/girder/girder_main.py
nlidatamanagement/views/girder/girder_mode.py
nlidatamanagement/views/girder/girder_new_folder.py
nlidatamanagement/views/girder/girder_preview.py
nlidatamanagement/views/girder/girder_setting.py
nlidatamanagement/views/tag/__init__.py
nlidatamanagement/views/tag/tag_main.py
nlidatamanagement/views/tag/tag_management.py
nlidatamanagement/views/zotero/__init__.py
nlidatamanagement/views/zotero/zotero_entry.py
nlidatamanagement/views/zotero/zotero_file_system.py
nlidatamanagement/views/zotero/zotero_main.py
nlidatamanagement/views/zotero/zotero_setting.py
nlidatamanagement-0.0.3.dist-info/LICENSE
nlidatamanagement-0.0.3.dist-info/METADATA
nlidatamanagement-0.0.3.dist-info/WHEEL
nlidatamanagement-0.0.3.dist-info/entry_points.txt
nlidatamanagement-0.0.3.dist-info/top_level.txt
nlidatamanagement-0.0.3.dist-info/RECORD
