Metadata-Version: 2.1
Name: nlidatamanagement
Version: 0.0.3
Summary: A tkinter GUI for uploading tagged data to Girder and Zotero.
Home-page: https://github.com/NutritionalLungImmunity/data-management
Author: Luis Sordo Vieira
Author-email: luis.sordovieira@medicine.ufl.edu
License: UNKNOWN
Project-URL: Bug Tracker, https://github.com/NutritionalLungImmunity/data-management/issues
Platform: UNKNOWN
Classifier: Programming Language :: Python :: 3
Classifier: License :: OSI Approved :: MIT License
Classifier: Operating System :: OS Independent
Requires-Python: >=3.6
Requires-Dist: flake8 (>=3.7.9)
Requires-Dist: pytest (>=5.4.1)
Requires-Dist: girder-client (>=3.1.0)
Requires-Dist: attrs (>=19.3.0)
Requires-Dist: pyzotero (>=1.4.16)
Requires-Dist: pandas (>=1.0.5)
Requires-Dist: pillow (>=8.0.1)
Requires-Dist: pytablewriter (>=0.58.0)
